{"code":200,"msg":"\u8bf7\u6c42\u6210\u529f","result":[{"p_catalog_id":"7","parent_id":"0","name":"\u6570\u7801\u5468\u8fb9","pic":"","is_deleted":"0","child":[{"p_catalog_id":"119","parent_id":"7","name":"\u81ea\u62cd\u6746","pic":"","is_deleted":"0"},{"p_catalog_id":"118","parent_id":"7","name":"\u5c4f\u5e55\u4fdd\u62a4\u819c","pic":"","is_deleted":"0"},{"p_catalog_id":"116","parent_id":"7","name":"Wacom\u7cfb\u5217","pic":"\/1472112184129.jpg","is_deleted":"0"},{"p_catalog_id":"112","parent_id":"7","name":"\u4ea4\u901a\u5361","pic":"\/product_catalog\/1465808719970.jpg","is_deleted":"0"},{"p_catalog_id":"103","parent_id":"7","name":"\u9f20\u952e","pic":"\/product_catalog\/1454061759825.jpg","is_deleted":"0"},{"p_catalog_id":"102","parent_id":"7","name":"U\u76d8","pic":"\/product_catalog\/1454061108683.jpg","is_deleted":"0"},{"p_catalog_id":"101","parent_id":"7","name":"\u8033\u673a","pic":"\/product_catalog\/1454060084922.png","is_deleted":"0"},{"p_catalog_id":"93","parent_id":"7","name":"\u7968\u52a1","pic":"\/product_catalog\/1454484273989.jpg","is_deleted":"0"},{"p_catalog_id":"50","parent_id":"7","name":"\u624b\u673a\u58f3","pic":"\/product_catalog\/1446017444813.jpg","is_deleted":"0"},{"p_catalog_id":"39","parent_id":"7","name":"\u79fb\u52a8\u7535\u6e90","pic":"\/product_catalog\/1446017382141.jpg","is_deleted":"0"},{"p_catalog_id":"40","parent_id":"7","name":"\u9f20\u6807\u57ab","pic":"\/product_catalog\/1446017408013.jpg","is_deleted":"0"},{"p_catalog_id":"41","parent_id":"7","name":"\u91d1\u5c5e\u8d34","pic":"\/product_catalog\/1446017422349.jpg","is_deleted":"0"}],"hot_product_list":[{"product_id":"8262","channel_id":"3","brand_id":"5","p_catalog_id":"101","supplier_type":"2","supplier_code":"1102013","name":"Censi \u58f0\u6c0f Moecen\u732b\u8033\u8033\u673a \u4e8c\u6b21\u5143 \u52a8\u6f2b \u5356\u840c \u5934\u6234\u5f0f \u84dd\u7259\u8033\u673a\u3010\u767d\u8272\u7248\u3011","cover_price":"299.00","brief":"","figure":"\/1469173640233.jpg","sell_time_start":"1469116800","sell_time_end":"1469721600"},{"product_id":"7752","channel_id":"3","brand_id":"421","p_catalog_id":"116","supplier_type":"2","supplier_code":"400003","name":"\u3010wacom\u3011\u6570\u4f4d\u677f\u753b\u677fctl471\u624b\u7ed8\u677fbamboo\u7535\u8111\u7ed8\u753b\u7535\u5b50\u7ed8\u56fe\u677fps","cover_price":"329.00","brief":"WACOM CTL471","figure":"\/supplier\/1467702094592.jpg","sell_time_start":"0","sell_time_end":"0"},{"product_id":"2361","channel_id":"3","brand_id":"5","p_catalog_id":"7","supplier_type":"2","supplier_code":"2101001","name":"\u3010\u53e4\u602a\u820d\u3011 \u51ac\u5b63\u6696\u6696 \u548c\u98ce\u624b\u673a\u88ab\u5957 \u4ed3\u9f20\u88ab\u7a9d","cover_price":"15.00","brief":"","figure":"\/1445418450175.jpg","sell_time_start":"1478772000","sell_time_end":"1445961600"},{"product_id":"8120","channel_id":"4","brand_id":"274","p_catalog_id":"41","supplier_type":"2","supplier_code":"802001","name":"\u3010\u781a\u6c60\u5de5\u4f5c\u5ba4\u3011\u5251\u7f51\u4e09 \u52513\u540c\u4eba\u5168\u95e8\u6d3e\u884d\u751flogo\u5468\u8fb9 \u91d1\u5c5e\u624b\u673a\u8d34\u3010\u94f6\u8272\u3011","cover_price":"30.00","brief":"","figure":"\/1468840600394.jpg","sell_time_start":"1468771200","sell_time_end":"1469376000"},{"product_id":"10652","channel_id":"3","brand_id":"5","p_catalog_id":"101","supplier_type":"2","supplier_code":"2101002","name":"\u3010\u6b6a\u74dc\u51fa\u54c1\u3011Spirit E666\u7cbe\u7075\u8033\u6735 \u5165\u8033\u5f0f\u8033\u673a cos\u6444\u5f71\u9053\u5177\u76f4\u64ad\u8033\u585e","cover_price":"99.00","brief":"","figure":"\/1478833408658.jpg","sell_time_start":"1478793600","sell_time_end":"1479398400"},{"product_id":"9709","channel_id":"3","brand_id":"305","p_catalog_id":"119","supplier_type":"1","supplier_code":"1102019","name":"\u3010ROCK\u3011\u54c6\u5566A\u68a6\u81ea\u62cd\u6746\u795e\u5668","cover_price":"49.00","brief":"","figure":"\/1475979038217.jpg","sell_time_start":"1478581200","sell_time_end":"1478581200"}]}]}